ergodicity/__init__.py
ergodicity/cases.py
ergodicity/configurations.py
ergodicity/custom_warnings.py
ergodicity/agents/__init__.py
ergodicity/agents/agent_pool.py
ergodicity/agents/agents.py
ergodicity/agents/evaluation.py
ergodicity/agents/evolutionary_nn.py
ergodicity/agents/portfolio.py
ergodicity/agents/probability_weighting.py
ergodicity/agents/sml.py
ergodicity/developer_tools/__init__.py
ergodicity/developer_tools/custom_samplers.py
ergodicity/developer_tools/stationarity.py
ergodicity/process/__init__.py
ergodicity/process/basic.py
ergodicity/process/constructor.py
ergodicity/process/custom_classes.py
ergodicity/process/default_values.py
ergodicity/process/definitions.py
ergodicity/process/discrete.py
ergodicity/process/increments.py
ergodicity/process/lib.py
ergodicity/process/multiplicative.py
ergodicity/process/with_memory.py
ergodicity/tools/__init__.py
ergodicity/tools/automate.py
ergodicity/tools/compute.py
ergodicity/tools/evaluate.py
ergodicity/tools/fit.py
ergodicity/tools/helper.py
ergodicity/tools/multiprocessing.py
ergodicity/tools/partial_sde.py
ergodicity/tools/preasymptotics.py
ergodicity/tools/research.py
ergodicity/tools/solve.py
ergodicity-0.3.19.dist-info/LICENSE
ergodicity-0.3.19.dist-info/METADATA
ergodicity-0.3.19.dist-info/WHEEL
ergodicity-0.3.19.dist-info/top_level.txt
ergodicity-0.3.19.dist-info/RECORD
